oscarapi/__init__.py
oscarapi/admin.py
oscarapi/apps.py
oscarapi/middleware.py
oscarapi/models.py
oscarapi/permissions.py
oscarapi/settings.py
oscarapi/signals.py
oscarapi/urls.py
oscarapi/basket/__init__.py
oscarapi/basket/operations.py
oscarapi/download/__init__.py
oscarapi/download/default.py
oscarapi/migrations/0001_initial.py
oscarapi/migrations/__init__.py
oscarapi/serializers/__init__.py
oscarapi/serializers/basket.py
oscarapi/serializers/checkout.py
oscarapi/serializers/exceptions.py
oscarapi/serializers/fields.py
oscarapi/serializers/hooks.py
oscarapi/serializers/login.py
oscarapi/serializers/product.py
oscarapi/serializers/utils.py
oscarapi/serializers/admin/__init__.py
oscarapi/serializers/admin/order.py
oscarapi/serializers/admin/partner.py
oscarapi/serializers/admin/product.py
oscarapi/serializers/admin/user.py
oscarapi/templates/rest_framework/api.html
oscarapi/tests/__init__.py
oscarapi/tests/utils.py
oscarapi/utils/__init__.py
oscarapi/utils/accessors.py
oscarapi/utils/attributes.py
oscarapi/utils/categories.py
oscarapi/utils/deprecations.py
oscarapi/utils/download.py
oscarapi/utils/exists.py
oscarapi/utils/files.py
oscarapi/utils/loading.py
oscarapi/utils/models.py
oscarapi/utils/request.py
oscarapi/utils/session.py
oscarapi/utils/settings.py
oscarapi/views/__init__.py
oscarapi/views/basic.py
oscarapi/views/basket.py
oscarapi/views/checkout.py
oscarapi/views/login.py
oscarapi/views/product.py
oscarapi/views/root.py
oscarapi/views/utils.py
oscarapi/views/admin/__init__.py
oscarapi/views/admin/order.py
oscarapi/views/admin/partner.py
oscarapi/views/admin/product.py
oscarapi/views/admin/user.py
django_oscar_api-3.3.0.dist-info/LICENSE
django_oscar_api-3.3.0.dist-info/METADATA
django_oscar_api-3.3.0.dist-info/WHEEL
django_oscar_api-3.3.0.dist-info/top_level.txt
django_oscar_api-3.3.0.dist-info/RECORD
