Metadata-Version: 2.1
Name: django-oscar-api
Version: 3.3.0
Summary: REST API module for django-oscar
Home-page: https://github.com/django-oscar/django-oscar-api
Author: Lars van de Kerkhof, Martijn Jacobs
Author-email: lars@permanentmarkers.nl, martijn@devopsconsulting.nl
License: BSD
Classifier: Development Status :: 5 - Production/Stable
Classifier: Environment :: Web Environment
Classifier: Framework :: Django
Classifier: Framework :: Django :: 3.2
Classifier: Intended Audience :: Developers
Classifier: License :: OSI Approved :: BSD License
Classifier: Operating System :: Unix
Classifier: Programming Language :: Python
Classifier: Programming Language :: Python :: 3
Classifier: Programming Language :: Python :: 3.7
Classifier: Programming Language :: Python :: 3.8
Classifier: Programming Language :: Python :: 3.9
Classifier: Programming Language :: Python :: 3.10
Classifier: Programming Language :: Python :: 3.11
Classifier: Topic :: Software Development :: Libraries :: Application Frameworks
Requires-Python: >=3.7
License-File: LICENSE
Requires-Dist: setuptools
Requires-Dist: django-oscar >=3.2
Requires-Dist: Django >=3.2
Requires-Dist: djangorestframework >=3.9
Provides-Extra: dev
Requires-Dist: coverage ; extra == 'dev'
Requires-Dist: wheel ; extra == 'dev'
Requires-Dist: easy-thumbnails ; extra == 'dev'
Requires-Dist: vdt.versionplugin.wheel ; extra == 'dev'
Requires-Dist: pylint ; extra == 'dev'
Requires-Dist: pylint-django ; extra == 'dev'
Requires-Dist: black >=23.1.0 ; extra == 'dev'
